COPYING
MANIFEST.in
README-ja.md
README.md
README.rst
setup.py
jacot/__init__.py
jacot/jacot.py
jacot.egg-info/PKG-INFO
jacot.egg-info/SOURCES.txt
jacot.egg-info/dependency_links.txt
jacot.egg-info/eager_resources.txt
jacot.egg-info/entry_points.txt
jacot.egg-info/requires.txt
jacot.egg-info/top_level.txt
jacot.egg-info/zip-safe
jacot/japanese/__init__.py
jacot/japanese/japanese.py