Metadata-Version: 1.1
Name: jacot
Version: 0.2.9
Summary: Japanese Auto character set Conversion On Tty
Home-page: https://github.com/saitoha/jacot
Author: Hayaki Saito (user@zuse.jp)
Author-email: user@zuse.jp
License: GPL v3
Keywords: japanese terminal
Platform: UNKNOWN
Classifier: Development Status :: 4 - Beta
Classifier: Topic :: Terminals
Classifier: Environment :: Console
Classifier: Intended Audience :: End Users/Desktop
Classifier: License :: OSI Approved :: GNU General Public License (GPL)
Classifier: Programming Language :: Python
